data_password_entropy/__init__.py
data_password_entropy/calc.py
data_password_entropy-1.0.dist-info/WHEEL
data_password_entropy-1.0.dist-info/METADATA
data_password_entropy-1.0.dist-info/RECORD
