Metadata-Version: 2.1
Name: data-password-entropy
Version: 1.0
Summary: Calculate password strength
Author-email: Oleh Alistratov <alistratov.dev@gmail.com>
Requires-Python: >=3.7
Classifier: Development Status :: 5 - Production/Stable
Classifier: Programming Language :: Python :: 3
Classifier: License :: OSI Approved :: Apache Software License
Classifier: Operating System :: OS Independent
Project-URL: Documentation, https://password-entropy.readthedocs.io/en/latest/
Project-URL: Homepage, https://github.com/alistratov/password-entropy-py
Project-URL: Issues, https://github.com/alistratov/password-entropy-py/issues
